evm_wallet/__init__.py
evm_wallet/_base_wallet.py
evm_wallet/async_wallet.py
evm_wallet/erc20.abi
evm_wallet/types.py
evm_wallet/utils.py
evm_wallet/wallet.py
evm_wallet-2.1.3.dist-info/LICENSE
evm_wallet-2.1.3.dist-info/METADATA
evm_wallet-2.1.3.dist-info/WHEEL
evm_wallet-2.1.3.dist-info/RECORD
