Metadata-Version: 2.1
Name: evm_wallet
Version: 2.1.3
Summary: The package, containing wrapper over EVM operations for interacting through Wallet entities
Home-page: https://github.com/CrocoFactory/evm-wallet
License: MIT
Author: Alexey
Author-email: axbelenkov@gmail.com
Requires-Python: >=3.11,<4.0
Classifier: Development Status :: 5 - Production/Stable
Classifier: Intended Audience :: Developers
Classifier: License :: OSI Approved :: MIT License
Classifier: Operating System :: MacOS
Classifier: Operating System :: Microsoft :: Windows
Classifier: Programming Language :: Python :: 3
Classifier: Programming Language :: Python :: 3.11
Classifier: Programming Language :: Python :: 3.12
Classifier: Programming Language :: Python :: 3 :: Only
Classifier: Topic :: Software Development :: Libraries :: Python Modules
Requires-Dist: web3 (>=6.12.0,<7.0.0)
Project-URL: Repository, https://github.com/CrocoFactory/evm-wallet
